enigma/__init__.py
enigma/core/__init__.py
enigma/core/machine.py
enigma/core/plugboard.py
enigma/core/reflector.py
enigma/core/rotor.py
enigma/data/__init__.py
enigma/data/reflectors.py
enigma/data/rotors.py
enigma/utils/cli/__init__.py
enigma/utils/cli/main.py
enigma/utils/gui/__init__.py
enigma/utils/gui/app.py
enigma_m4-0.4.0.dist-info/licenses/LICENSE
enigma_m4-0.4.0.dist-info/METADATA
enigma_m4-0.4.0.dist-info/WHEEL
enigma_m4-0.4.0.dist-info/top_level.txt
enigma_m4-0.4.0.dist-info/RECORD
