Metadata-Version: 2.4
Name: enigma-m4
Version: 0.4.0
Summary: A modern, fully tested Enigma machine simulator in Python.
Author: Łukasz Perek
License: MIT License
Requires-Python: >=3.10
License-File: LICENSE
Provides-Extra: dev
Requires-Dist: pytest; extra == "dev"
Requires-Dist: pytest-cov; extra == "dev"
Requires-Dist: black; extra == "dev"
Requires-Dist: flake8; extra == "dev"
Requires-Dist: ruff; extra == "dev"
Requires-Dist: mypy; extra == "dev"
Dynamic: license-file
